ez_cqrs/__init__.py
ez_cqrs/_framework.py
ez_cqrs/_typing.py
ez_cqrs/components.py
ez_cqrs/py.typed
ez_cqrs/testing.py
ez_cqrs/utils/__init__.py
ez_cqrs/utils/cli.py
ez_cqrs/utils/dates.py
ez_cqrs-6.1.7.dist-info/METADATA
ez_cqrs-6.1.7.dist-info/WHEEL
ez_cqrs-6.1.7.dist-info/licenses/LICENSE
ez_cqrs-6.1.7.dist-info/RECORD
