Metadata-Version: 2.1
Name: ez_cqrs
Version: 6.1.7
Project-URL: Documentation, https://github.com/Tomperez98/ez-cqrs#readme
Project-URL: Issues, https://github.com/Tomperez98/ez-cqrs/issues
Project-URL: Source, https://github.com/Tomperez98/ez-cqrs
Author-email: Tomas Perez Alvarez <tomasperezalvarez@gmail.com>
License-File: LICENSE
Classifier: Programming Language :: Python :: Implementation :: CPython
Classifier: Programming Language :: Python :: Implementation :: PyPy
Requires-Python: >=3.9
Requires-Dist: result<1
Provides-Extra: dev
Requires-Dist: pip-tools==7.3.0; extra == 'dev'
Requires-Dist: pyrgo>=2; extra == 'dev'
Requires-Dist: pytest-asyncio; extra == 'dev'
Requires-Dist: pytest-cov; extra == 'dev'
